LICENSE
MANIFEST.in
README.md
setup.cfg
setup.py
congee/__init__.py
congee.egg-info/PKG-INFO
congee.egg-info/SOURCES.txt
congee.egg-info/dependency_links.txt
congee.egg-info/entry_points.txt
congee.egg-info/top_level.txt